debugtools/__init__.py
debugtools/formatter.py
debugtools/middleware/__init__.py
debugtools/middleware/xviewmiddleware.py
debugtools/panels/__init__.py
debugtools/panels/view.py
debugtools/static/debugtools/jquery.debug.js
debugtools/templates/debugtools/sql_queries.html
debugtools/templates/debugtools/view_panel.html
debugtools/templatetags/__init__.py
debugtools/templatetags/debug_tags.py
debugtools/templatetags/debugtools_tags.py
debugtools/utils/__init__.py
debugtools/utils/xview.py
django_debugtools-2.0.dist-info/AUTHORS
django_debugtools-2.0.dist-info/LICENSE
django_debugtools-2.0.dist-info/METADATA
django_debugtools-2.0.dist-info/WHEEL
django_debugtools-2.0.dist-info/top_level.txt
django_debugtools-2.0.dist-info/RECORD
